housing_violations_nyc/__init__.py
housing_violations_nyc/housing_violations_nyc.py
housing_violations_nyc-0.1.1.dist-info/LICENSE
housing_violations_nyc-0.1.1.dist-info/METADATA
housing_violations_nyc-0.1.1.dist-info/WHEEL
housing_violations_nyc-0.1.1.dist-info/RECORD
