Metadata-Version: 2.1
Name: housing_violations_nyc
Version: 0.1.1
Summary: Python package that processes and explores NYC Housing Violation data.
License: MIT
Author: Jenna Swartz
Requires-Python: >=3.12,<4.0
Classifier: License :: OSI Approved :: MIT License
Classifier: Programming Language :: Python :: 3
Classifier: Programming Language :: Python :: 3.12
Requires-Dist: matplotlib (>=3.9.3,<4.0.0)
Requires-Dist: pandas (>=2.2.3,<3.0.0)
Requires-Dist: requests (>=2.32.3,<3.0.0)
Requires-Dist: seaborn (>=0.13.2,<0.14.0)
